Metadata-Version: 2.1
Name: bootcamp-for-python-basic-data-structures
Version: 0.0.1
Summary: A collection of basic data structures in Python
Home-page: https://abenezerkb.github.io/basic-python-data-structure/
Author: Abenezer Angamo
Author-email: aben.jacob3@gmail.com
License: UNKNOWN
Platform: UNKNOWN
Classifier: Programming Language :: Python :: 3
Classifier: License :: OSI Approved :: MIT License
Classifier: Operating System :: OS Independent
Requires-Python: >=3.6
